pdf2anki/__init__.py
pdf2anki/main.py
pdf2anki-0.1.2.dist-info/LICENSE
pdf2anki-0.1.2.dist-info/METADATA
pdf2anki-0.1.2.dist-info/WHEEL
pdf2anki-0.1.2.dist-info/entry_points.txt
pdf2anki-0.1.2.dist-info/top_level.txt
pdf2anki-0.1.2.dist-info/RECORD
