Metadata-Version: 2.1
Name: pdf2anki
Version: 0.1.2
Summary: A Python package to create Anki cards from PDFs using OpenAI.
Home-page: https://github.com/hipnologo/pdf2anki
Author: Fabio Carvalho
Author-email: hipnologo@gmail.com
Classifier: Development Status :: 3 - Alpha
Classifier: Intended Audience :: Developers
Classifier: License :: OSI Approved :: MIT License
Classifier: Programming Language :: Python :: 3.6
License-File: LICENSE
Requires-Dist: openai >=0.27.0
Requires-Dist: PyPDF2 >=1.26.0
